polaris_terminal/__init__.py
polaris_terminal/cli.py
polaris_terminal/terminal.py
polaris_terminal-0.1.1.dist-info/licenses/LICENSE
polaris_terminal-0.1.1.dist-info/METADATA
polaris_terminal-0.1.1.dist-info/WHEEL
polaris_terminal-0.1.1.dist-info/entry_points.txt
polaris_terminal-0.1.1.dist-info/top_level.txt
polaris_terminal-0.1.1.dist-info/RECORD
